{
    "prepare_queue": {
        "installed": [],
        "uninstalled": []
    },
    "config_munge": {
        "files": {}
    },
    "installed_plugins": {
        "cordova-plugin-whitelist": {
            "PACKAGE_NAME": "io.cordova.hellocordova"
        },
        "cordova-plugin-xfyun": {
            "NSMICROPHONEUSAGEDESCRIPTION": "请点击'好'以允许访问。",
            "PACKAGE_NAME": "io.cordova.hellocordova"
        },
        "cordova-plugin-android-fingerprint-auth": {
            "PACKAGE_NAME": "io.cordova.hellocordova"
        }
    },
    "dependent_plugins": {}
}